[
    {
        "username": "victorursu",
        "email": "victor.ursu02@e-uvt.ro",
        "password": "$2y$10$FwDJ1e0mtagTkRIuCp9diurfLVui7bFo4Gz6tOWIMfpmWF8AepbdS"
    },
    {
        "username": "victorursu",
        "email": "victor.ursu02@e-uvt.ro",
        "password": "$2y$10$oXirrWcBPjK9N6p6Ca1U1.k2n9iozeL03CtI\/a\/9TcGBLfgIi.lQe"
    },
    {
        "username": "victorursu999",
        "email": "victor.ursu02@e-uvt.ro",
        "password": "$2y$10$eqHnNeHikfiwL89EINPeuOR24c2VZWlUaOTxGCDSRFd79QmlYTfeK"
    },
    {
        "username": "juju",
        "email": "juju02@e-uvt.ro",
        "password": "$2y$10$HAM0J77tN0McWlfNcGKJieo0auZ5i\/0TVh\/qpd7JwBTj.zGurX3Zm"
    },
    {
        "username": "alexandru444",
        "email": "alexandru2000@gmail.com",
        "password": "$2y$10$o2\/4YzSBkhpKnLN3QkfU4.IDDwzlywypDBEXTPC8q5a6D5SaqbRea"
    },
    {
        "username": "alex",
        "email": "victorursu29@yahoo.com",
        "password": "$2y$10$Lnb9fppVKpXVqVJxfGQLbeyqwcM9RqCTqpzK2OYE5X6TVMcKg.KHu"
    }
]